myimagelib/__init__.py
myimagelib/corrLib.py
myimagelib/myImageLib.py
myimagelib/pivLib.py
myimagelib-2.0.1.dist-info/METADATA
myimagelib-2.0.1.dist-info/WHEEL
myimagelib-2.0.1.dist-info/licenses/LICENSE
myimagelib-2.0.1.dist-info/RECORD
