Metadata-Version: 2.4
Name: myimagelib
Version: 2.0.1
Summary: Image IO, correlation, PIV, particle tracking tools collection.
Project-URL: Homepage, https://zloverty.github.io/mylib/
Project-URL: Bug Tracker, https://github.com/ZLoverty/mylib/issues
Author-email: Zhengyang Liu <liuzy19911112@gmail.com>
License-File: LICENSE
Classifier: License :: OSI Approved :: MIT License
Classifier: Operating System :: OS Independent
Classifier: Programming Language :: Python :: 3
Requires-Python: >=3.12
Requires-Dist: nd2reader
Requires-Dist: numpy
Requires-Dist: pandas
Requires-Dist: psutil
Requires-Dist: scikit-image
Requires-Dist: scikit-learn
Requires-Dist: scipy
